setup.cfg
setup.py
pynoti/__init__.py
pynoti/noti.py
pynoti.egg-info/PKG-INFO
pynoti.egg-info/SOURCES.txt
pynoti.egg-info/dependency_links.txt
pynoti.egg-info/not-zip-safe
pynoti.egg-info/top_level.txt